twse_api_sdk/__init__.py
twse_api_sdk/twse.py
twse_api_sdk-0.1.0.dist-info/LICENSE
twse_api_sdk-0.1.0.dist-info/WHEEL
twse_api_sdk-0.1.0.dist-info/METADATA
twse_api_sdk-0.1.0.dist-info/RECORD
